<?xml version="1.0" encoding="UTF-8" standalone="yes"?>
<addon id="plugin.video.sweettv"
       name="Sweet.TV"
       version="2026.04.05"
       provider-name="kodi-sweet.tv">
  <requires>
    <import addon="xbmc.python" version="3.0.0"/>
    <import addon="script.module.requests" version="2.9.7"/>
    <import addon="inputstream.adaptive" optional="true"/>
    <import addon="service.iptv.manager"/>
    <import addon="pvr.iptvsimple" optional="true"/>
  </requires>
  <extension point="xbmc.python.pluginsource" library="addon.py">
    <provides>video</provides>
  </extension>
  <extension point="xbmc.service" library="service.py" start="startup"/>
  <!-- IPTV Manager integration endpoints -->
  <extension point="xbmc.python.pluginsource" library="addon.py">
    <provides>iptv</provides>
  </extension>
  <extension point="xbmc.addon.metadata">
    <!-- IPTV Manager configuration -->
    <iptv_manager>
      <channels_uri>plugin://plugin.video.sweettv/?action=iptv_channels&amp;port={port}</channels_uri>
      <epg_uri>plugin://plugin.video.sweettv/?action=iptv_epg&amp;port={port}</epg_uri>
    </iptv_manager>
    <summary lang="en_GB">Sweet.TV streaming service</summary>
    <summary lang="sk_SK">Sweet.TV streamovacia sluzba</summary>
    <description lang="en_GB">Watch Sweet.TV live channels, EPG, archive and movies in Kodi. Integrates with IPTV Manager for native TV experience.</description>
    <description lang="sk_SK">Sledujte Sweet.TV live kanaly, EPG, archiv a filmy v Kodi. Integracia s IPTV Manager pre nativny TV zazitok.</description>
    <disclaimer lang="en_GB">This addon requires a valid Sweet.TV subscription.</disclaimer>
    <platform>all</platform>
    <license>GPL-3.0</license>
    <source>https://github.com/odlevakp/kodi-sweet.tv</source>
    <news>v2026.04.05 - Initial release with live TV, EPG, and IPTV Manager integration</news>
  </extension>
</addon>
